skyrc_gsm015/__init__.py
skyrc_gsm015/igc.py
skyrc_gsm015/parse.py
skyrc_gsm015/skyrc_gsm015.py
skyrc_gsm015/skyrc_usb.py
skyrc_gsm015-0.1.4.dist-info/METADATA
skyrc_gsm015-0.1.4.dist-info/WHEEL
skyrc_gsm015-0.1.4.dist-info/entry_points.txt
skyrc_gsm015-0.1.4.dist-info/licenses/LICENSE
skyrc_gsm015-0.1.4.dist-info/RECORD
