Metadata-Version: 2.4
Name: skyrc_gsm015
Version: 0.1.4
Summary: Command line Python code to extract track logs from SkyRC GSM-015 GNSS Speed Meter
Project-URL: Homepage, https://github.com/matburnham/skyrc-gsm015
Project-URL: Issues, https://github.com/matburnham/skyrc-gsm015/issues
Author-email: Mat Burnham <matburnham@gmail.com>
License-Expression: MIT
License-File: LICENSE
Classifier: Operating System :: OS Independent
Classifier: Programming Language :: Python :: 3
Requires-Python: >=3.8
Requires-Dist: aerofiles>=1.4.0
Requires-Dist: pyusb>=1.3.1
Provides-Extra: tqdm
Requires-Dist: tqdm>=4.67.1; extra == 'tqdm'
